{
	"id" : 1035984567,
	"date" : "2017-03-12T07:13:00.000Z",
	"image": {
		"owner": "ТАСС"
	},
	"header" : "В Батуми против участников беспорядков провели спецоперацию",
	"content": [
		"В Батуми местные власти провели спецоперацию против участников массовых беспорядков с привлечением полиции и спецназа, в результате которой пострадало более 20 человек. В ходе вытеснения протестующих с центральных улиц города, полиция применяла резиновые пули.",
		"Причиной массовых беспорядков стало задержание шести местных жителей. Горожане вышли на улицы, требуя освободить задержанных. Участники акции блокировали улицы, поджигали и переворачивали машины, забрасывали полицейских камнями. Сообщается, что в протесте принимает участие несколько тысяч человек."
	]
}
