{
	"id" : 1169943650,
	"date" : "2017-03-10T16:51:00.000Z",
	"image": {
		"owner": "Reuters"
	},
	"header" : "В результате аварии вертолета в Стамбуле погибли семь человек",
	"content": [
		"Сегодня в Стамбуле в результате аварии вертолета погибли семь человек, четверо из которых — граждане России. По предварительным данным крушение произошло из-за плохих погодных условий — сообщается, что в момент происшествия был сильный туман.",
		"Вертолет рухнул в результате столкновения с телебашней. Виновниками являются члены экипажа летательного аппарата. По информации турецких СМИ россияне, находившиеся на борту, — бизнесмены из Санкт-Петербурга, которые летели из Стамбула в провинцию Биледжек, где у них была намечена деловая встреча."
	]
}
