{
	"id" : 4114532379,
	"date" : "2017-03-06T15:55:00.000Z",
	"image": {
		"owner": "Соцсети"
	},
	"header" : "В Сирии погиб еще один российский военнослужащий",
	"content": [
		"2 марта при контратаке боевиков ИГ в районе Пальмиры погиб рядовой-контрактник Артем Горбунов. Этот факт подтвердили в Министерстве обороны России. Сообщается, что Артем Горбунов выполнял задачи по охране группы российских военных советников. «Военнослужащий представлен к государственной награде посмертно», — добавили в военном ведомстве.",
		"Ранее также сообщалось, что 12 февраля 2017 года в Сирии погиб еще один российский военнослужащий из Челябинской области Иван Слышкин. Однако в Минобороны эту информацию опровергают, заявив, что Слышкин «в 2013 году был уволен в установленном порядке в запас»."
	]
}
