{
	"id" : 461283590,
	"date" : "2017-07-02T10:10:00.000Z",
	"image": {
		"owner": "ТАСС"
	},
	"header" : "В результате ДТП в Татарстане погибли 14 человек",
	"content": [
		"Сегодня в результате столкновения и последующего возгорания автобуса, следовавшего по маршруту Самара—Ижевск, и грузовика, оказавшегося бензовозом, в Татарстане погибли 14 человек. Следственный комитет России уже возбудил два уголовных дела по статьям 264, ч.5 (нарушение правил дорожного движения и эксплуатации транспортных средств, повлекшее по неосторожности смерть двух или более лиц) и ч. 3 ст. 238 УК РФ (оказание услуг, не отвечающих требованиям безопасности, повлекшее по неосторожности смерть двух или более лиц).",
		"В настоящий момент задержаны гендиректор перевозчика, автобус которого попал в ДТП, а также водитель автобуса, находящийся в больнице. Премьер-министр Татарстана Алексей Песошин и глава регионального МЧС Рафис Хабибуллин прибыли на место трагедии. Сегодняшний день объявлен в республике днем траура."
	]
}
