{
	"id" : 732066320,
	"date" : "2017-02-02T16:16:00.000Z",
	"image": {
		"owner": "Reuters"
	},
	"header" : "Правительство Великобритании опубликовало план выхода из ЕС",
	"content": [
		"Правительство Великобритании опубликовало на своем сайте «Белую книгу» — документ, содержащий 12 положений, которые были озвучены премьером в своей программной речи.",
		"Среди прочего в документе говорится о беспошлинной торговле после выхода из Евросоюза и о таможенном регламенте.",
		"Напомним, что что Brexit уже одобрен Палатой общин — нижней палатой британского парламента, но для начала реализации этой процедуры еще требуется одобрение Палаты лордов. Голосование в этой палате намечено на февраль."
	]
}
