{
	"id" : 868077280,
	"date" : "2017-03-30T15:32:00.000Z",
	"image": {
		"owner": "ТАСС"
	},
	"header" : "Мосгорсуд признал законным административный арест Навального",
	"content": [
		"Мосгорсуд признал законным административный арест Алексея Навального на 15 суток, назначенный ему за сопротивление сотрудникам полиции при задержании во время несогласованной с властями акции в центре Москвы 26 марта.",
		"В ответ Навальный просил отменить постановление об административном аресте. «Я участвовал в законном, в мирном митинге, шествии. Я шел спокойно по тротуару, прибежали полицейские и, ничего не говоря, не предъявляя, потащили в автобус», — заявил руководитель ФБК. Он также добавил, что на ознакомление с протоколом по статье 19.3 КоАП РФ (сопротивление сотрудникам полиции) ему дали всего пять минут."
	]
}
