{
	"id" : 911672751,
	"date" : "2017-07-06T15:12:00.000Z",
	"image": {
		"owner": "ТАСС"
	},
	"header" : "В СКР заявили о раскрытии убийства мэра Сергиева Посада в 2011 году",
	"content": [
		"Следственный комитет России заявил, что дело об убийстве мэра Сергиева Посада Евгения Душко, которое было совершено в августе 2011 года, раскрыто. По версии следствия убийство градоначальника — дело рук банды Константина Пискарева, который больше известен под кличкой Костя Большой. Его банда была создана в 1999 году «для совершения убийств граждан»",
		"Евгений Душко, глава подмосковного Сергиева Посада, был расстрелян 22 августа 2011 года, когда садился в свой автомобиль Volvo S60. Из семи пуль, выпущенных киллером, в градоначальника попали три."
	]
}
