[{
		"date" : "2017-04-11T17:17:00.000Z",
		"header" : "В Москве объявлено штормовое предупреждение"
	}, {
		"date" : "2017-04-11T15:57:00.000Z",
		"header" : "Трамп подписал протокол о вступлении Черногории в НАТО"
	}, {
		"date" : "2017-04-11T13:35:00.000Z",
		"header" : "Евгений Евтушенко похоронен в Переделкино"
	}, {
		"date" : "2017-04-11T11:55:00.000Z",
		"header" : "Минобороны сообщило о гибели двух российских военных в Сирии"
	}, {
		"date" : "2017-04-11T00:12:00.000Z",
		"header" : "New York Times получила Пулитцеровскую премию за материалы о влиянии России"
	}]
