[{
		"date" : "2017-04-02T17:12:00.000Z",
		"header" : "Республиканская партия Армении заявила о своей победе на выборах"
	}, {
		"date" : "2017-04-02T15:41:00.000Z",
		"header" : "Ильдар Дадин задержан в Москве во время одиночного пикета"
	}, {
		"date" : "2017-04-02T09:24:00.000Z",
		"header" : "Более 400 человек приняли участие в оппозиционной акции в Новосибирске"
	}, {
		"date" : "2017-04-02T07:45:00.000Z",
		"header" : "Смотритель храма в Пакистане убил 20 прихожан"
	}, {
		"date" : "2017-04-02T04:22:00.000Z",
		"header" : "«Лужники» будут представлены комиссии FIFA в мае"
	}]
