[{
	"date" : "2017-08-17T00:00:00.000Z",
	"header" : "Советник Трампа Стив Бэннон уходит в отставку"
}, {
	"date" : "2017-08-17T00:00:00.000Z",
	"header" : "«Краснодар» обыграл «Црвену Звезду» — 3:2"
}, {
	"date" : "2017-08-17T00:00:00.000Z",
	"header" : "Лидер «Шалтая-Болтая» отозвал апелляцию на приговор"
}, {
	"date" : "2017-08-17T00:00:00.000Z",
	"header" : "Максим Товкайло возглавит сайт «Ведомостей»"
}, {
	"date" : "2017-08-17T00:00:00.000Z",
	"header" : "«Реал» выиграл Суперкубок Испании"
}]
