[{
		"date" : "2016-12-19T17:05:00.000Z",
		"header" : "В Анкаре в результате покушения убит посол России Андрей Карлов"
	},{
		"date" : "2016-12-19T13:41:00.000Z",
		"header" : "ЕС продлил санкции в отношении России до 31 июля 2017 года"
	},{
		"date" : "2016-12-19T09:48:00.000Z",
		"header" : "Более 30 человек погибли в Иркутске в результате отравления «Боярышником»"
	},{
		"date" : "2016-12-19T05:30:00.000Z",
		"header" : "В результате аварийной посадки самолета минобороны 16 военнослужащих получили тяжелые травмы"
	},{
		"date" : "2016-12-19T05:25:00.000Z",
		"header" : "Центробанк отозвал лицензии у четырех банков"
	},{
		"date" : "2016-12-19T04:27:00.000Z",
		"header" : "Победительницей конкурса «Мисс мира» стала участница из Пуэрто-Рико"
	}]
